kskit/__init__.py
kskit/__main__.py
kskit/core.py
kskit/crypto.py
kskit/deid_mammogram.py
kskit/dicom2png.py
kskit/helpers.py
kskit/java.py
kskit/password.py
kskit/test_deid_mammogram.py
kskit/test_df2dicom.py
kskit/voo.py
kskit/dicom/__init__.py
kskit/dicom/deid_mammogram.py
kskit/dicom/df2dicom.py
kskit/dicom/dicom2df.py
kskit/dicom/get_dicom.py
kskit/dicom/utils.py
kskit/test_cases/__init__.py
kskit/test_cases/cases.py
kskit-0.0.10.dist-info/LICENSE
kskit-0.0.10.dist-info/METADATA
kskit-0.0.10.dist-info/WHEEL
kskit-0.0.10.dist-info/top_level.txt
kskit-0.0.10.dist-info/RECORD
