Metadata-Version: 2.1
Name: kskit
Version: 0.0.10
Summary: Cancer screening analysis module build on Python
Home-page: https://github.com/Epiconcept-Paris/kskit
Author: Francisco Orchard
Author-email: f.orchard@epiconcept.fr
License: MIT License
License-File: LICENSE
Requires-Dist: paramiko
Requires-Dist: fabric
Requires-Dist: easyocr
Requires-Dist: cryptography
Requires-Dist: opencv-python (==4.5.5.64)
Requires-Dist: pydicom
Requires-Dist: Numpy
Requires-Dist: matplotlib
Requires-Dist: pynetdicom
Requires-Dist: requests
Requires-Dist: xmltodict
Requires-Dist: pandas
Requires-Dist: pyarrow
Requires-Dist: python-barcode[images]
Requires-Dist: qrcode
Requires-Dist: pyzbar[scripts]
Requires-Dist: opencv-python
Requires-Dist: pycryptodome
Requires-Dist: H5py
Requires-Dist: imageio
Requires-Dist: tqdm
Requires-Dist: pillow
Requires-Dist: gdcm
